pynoaa/__init__.py
pynoaa/api.py
noaapy-0.5.0.dist-info/LICENSE.txt
noaapy-0.5.0.dist-info/METADATA
noaapy-0.5.0.dist-info/WHEEL
noaapy-0.5.0.dist-info/top_level.txt
noaapy-0.5.0.dist-info/RECORD
